prometheus_ecs_discoverer/__init__.py
prometheus_ecs_discoverer/caching.py
prometheus_ecs_discoverer/discovery.py
prometheus_ecs_discoverer/fetching.py
prometheus_ecs_discoverer/main.py
prometheus_ecs_discoverer/marshalling.py
prometheus_ecs_discoverer/settings.toml
prometheus_ecs_discoverer/telemetry.py
prometheus_ecs_discoverer/toolbox.py
prometheus_ecs_discoverer-3.3.5.dist-info/LICENSE
prometheus_ecs_discoverer-3.3.5.dist-info/WHEEL
prometheus_ecs_discoverer-3.3.5.dist-info/METADATA
prometheus_ecs_discoverer-3.3.5.dist-info/RECORD
