Metadata-Version: 2.1
Name: prometheus-ecs-discoverer
Version: 3.3.5
Summary: Prometheus Service Discovery for AWS ECS
Home-page: https://github.com/trallnag/prometheus-ecs-discoverer
License: Apache-2.0
Keywords: prometheus,aws,ecs,metrics
Author: Tim Schwenke
Author-email: tim.schwenke@trallnag.com
Requires-Python: >=3.9,<4.0
Classifier: License :: OSI Approved :: Apache Software License
Classifier: Programming Language :: Python :: 3
Classifier: Programming Language :: Python :: 3.9
Requires-Dist: boto3 (>=1.16.00,<2.0.0)
Requires-Dist: dynaconf (>=3.1.2,<4.0.0)
Requires-Dist: loguru (>=0.5.3,<0.6.0)
Requires-Dist: prettyprinter (>=0.18.0,<0.19.0)
Requires-Dist: prometheus-client (>=0.8.0,<0.9.0)
Project-URL: Repository, https://github.com/trallnag/prometheus-ecs-discoverer
